{
  "book": [
    {
      "id": "14a4",
      "title": "성서고고학 대백과사전4(ㅈ-ㅎ) (ㅈ-ㅎ)",
      "author": "원용국",
      "image": "https://shopping-phinf.pstatic.net/main_3267092/32670925633.20221019140246.jpg",
      "description": "1",
      "isbn": "9791190863957"
    },
    {
      "id": "13b7",
      "title": "그림자를 이으면 길이 된다 (피해자에서 생존자, 그리고 감시자가 된 마녀 D의 사법연대기)",
      "author": "D",
      "image": "https://shopping-phinf.pstatic.net/main_3374483/33744837651.20230919130727.jpg",
      "description": "제목이 독특하다.",
      "isbn": "9788972970521"
    },
    {
      "id": "8741",
      "title": "나의 일기조각",
      "author": "S",
      "image": "https://shopping-phinf.pstatic.net/main_4005922/40059220627.20230516144808.jpg",
      "description": "",
      "isbn": "9791141027360"
    },
    {
      "id": "1172",
      "title": "파우스트 (Faust)",
      "author": "괴테",
      "image": "https://shopping-phinf.pstatic.net/main_3244154/32441546622.20230905101121.jpg",
      "description": "친구들과의 독서 토론회의 첫번째 작품이었는데 내가 고른거에도 불구하고 진짜 재미 없었다. 사실 두번째 시도였는데 너무 재미 없어서 3/4까지 읽고 그만뒀는데, \n재미 없던 이유는\n1. 기본 바탕 지식이 너무 필요하고\n2. 지들만 신나있다 ",
      "isbn": "9788932404363"
    }
  ]
}